idun_data_models/__init__.py
idun_data_models/data_streams.py
idun_data_models/device.py
idun_data_models/parameters.py
idun_data_models/py.typed
idun_data_models/rest_device.py
idun_data_models/rest_metadata.py
idun_data_models/rest_recording.py
idun_data_models/validation.py
idun_data_models/websocket_data_model.py
idun_data_models-0.3.6.dist-info/METADATA
idun_data_models-0.3.6.dist-info/WHEEL
idun_data_models-0.3.6.dist-info/RECORD
