Metadata-Version: 2.1
Name: idun_data_models
Version: 0.3.6
Summary: 
Author: Konstantinos Samaras-Tsakiris
Author-email: konstantinos@iduntechnologies.com
Requires-Python: >=3.10,<4.0
Classifier: Programming Language :: Python :: 3
Classifier: Programming Language :: Python :: 3.10
Classifier: Programming Language :: Python :: 3.11
Requires-Dist: pydantic (>=1.10,<2.0)
